llm_wrapper/__init__.py
llm_wrapper/chains/__init__.py
llm_wrapper/chains/long_text_processing_chain.py
llm_wrapper/constants/__init__.py
llm_wrapper/constants/azure.py
llm_wrapper/constants/input_data.py
llm_wrapper/constants/prompt.py
llm_wrapper/constants/vertex_ai.py
llm_wrapper/defaults/__init__.py
llm_wrapper/defaults/azure_defaults.py
llm_wrapper/defaults/general_defaults.py
llm_wrapper/defaults/long_text_chain.py
llm_wrapper/defaults/vertex_ai.py
llm_wrapper/domain/__init__.py
llm_wrapper/domain/configuration.py
llm_wrapper/domain/enumerables.py
llm_wrapper/domain/input_data.py
llm_wrapper/domain/prompt_dto.py
llm_wrapper/domain/response.py
llm_wrapper/exceptions/__init__.py
llm_wrapper/exceptions/validation_input_data_exceptions.py
llm_wrapper/models/__init__.py
llm_wrapper/models/abstract.py
llm_wrapper/models/azure_base.py
llm_wrapper/models/azure_llama2.py
llm_wrapper/models/azure_mistral.py
llm_wrapper/models/azure_openai.py
llm_wrapper/models/vertexai_base.py
llm_wrapper/models/vertexai_gemini.py
llm_wrapper/models/vertexai_palm.py
llm_wrapper/utils/__init__.py
llm_wrapper/utils/io_utils.py
llm_wrapper/utils/logger_utils.py
llm_wrapper/utils/long_text_processing_utils.py
llm_wrapper_allegro-0.0.1.1.dist-info/LICENSE
llm_wrapper_allegro-0.0.1.1.dist-info/METADATA
llm_wrapper_allegro-0.0.1.1.dist-info/WHEEL
llm_wrapper_allegro-0.0.1.1.dist-info/RECORD
