Metadata-Version: 2.1
Name: llm-wrapper-allegro
Version: 0.0.1.1
Summary: 
Author: Allegro Opensource
Author-email: opensource@allegro.com
Requires-Python: >=3.10,<4.0
Classifier: Programming Language :: Python :: 3
Classifier: Programming Language :: Python :: 3.10
Classifier: Programming Language :: Python :: 3.11
Classifier: Programming Language :: Python :: 3.12
Requires-Dist: aioresponses (>=0.7.6,<0.8.0)
Requires-Dist: fsspec (>=2023.6.0,<2024.0.0)
Requires-Dist: google-cloud-aiplatform (==1.38.0)
Requires-Dist: langchain (>=0.0.351,<0.0.352)
Requires-Dist: openai (>=0.27.8,<0.28.0)
Requires-Dist: pandas (>=2.0.3,<3.0.0)
Requires-Dist: pydantic (==1.10.13)
Requires-Dist: pydash (>=7.0.6,<8.0.0)
Requires-Dist: tiktoken (>=0.4.0,<0.5.0)
Requires-Dist: transformers (>=4.34.1,<5.0.0)
